SiPANN/__init__.py
SiPANN/comp.py
SiPANN/import_nn.py
SiPANN/nn.py
SiPANN/scee.py
SiPANN/scee_int.py
SiPANN/scee_opt.py
SiPANN/ANN/TIGHT_ANGLE_BENT_RAND/Import.pkl
SiPANN/ANN/TIGHT_ANGLE_BENT_RAND/model.data-00000-of-00001
SiPANN/ANN/TIGHT_ANGLE_BENT_RAND/model.index
SiPANN/ANN/TIGHT_ANGLE_BENT_RAND/model.meta
SiPANN/ANN/TIGHT_ANGLE_GAP/Import.pkl
SiPANN/ANN/TIGHT_ANGLE_GAP/model.data-00000-of-00001
SiPANN/ANN/TIGHT_ANGLE_GAP/model.index
SiPANN/ANN/TIGHT_ANGLE_GAP/model.meta
SiPANN/ANN/TIGHT_ANGLE_STRAIGHT/Import.pkl
SiPANN/ANN/TIGHT_ANGLE_STRAIGHT/model.data-00000-of-00001
SiPANN/ANN/TIGHT_ANGLE_STRAIGHT/model.index
SiPANN/ANN/TIGHT_ANGLE_STRAIGHT/model.meta
SiPANN/COUPLER/split_100_0.npz
SiPANN/COUPLER/split_10_90.npz
SiPANN/COUPLER/split_20_80.npz
SiPANN/COUPLER/split_30_70.npz
SiPANN/COUPLER/split_40_60.npz
SiPANN/COUPLER/split_50_50.npz
SiPANN/LR/DC_coeffs.pkl
SiPANN/LR/R_bent.pkl
SiPANN/LR/R_bent_wide.pkl
SiPANN/LR/R_gap0.pkl
SiPANN/LR/R_gap1.pkl
SiPANN/LR/R_straight.pkl
SiPANN-2.0.0.dist-info/LICENSE
SiPANN-2.0.0.dist-info/METADATA
SiPANN-2.0.0.dist-info/WHEEL
SiPANN-2.0.0.dist-info/top_level.txt
SiPANN-2.0.0.dist-info/RECORD
