Metadata-Version: 2.1
Name: SiPANN
Version: 2.0.0
Summary: Artifical Neural Networks for use with Silicon Photonics
Home-page: https://github.com/contagon/SiPANN
Author: Easton Potokar, Alec Hammond, R Scott Collings
Author-email: eastonpots@byu.edu
Keywords: artificial neural networks silicon photonics coupling
Classifier: Development Status :: 4 - Beta
Classifier: Intended Audience :: Developers
Classifier: Topic :: Software Development :: Build Tools
Classifier: License :: OSI Approved :: MIT License
Classifier: Programming Language :: Python :: 3
Classifier: Programming Language :: Python :: 3.7
Classifier: Programming Language :: Python :: 3.8
Classifier: Programming Language :: Python :: 3.9
Classifier: Programming Language :: Python :: 3.10
License-File: LICENSE
Requires-Dist: tensorflow
Requires-Dist: gdspy (>=1.5.2)
Requires-Dist: scikit-rf
Requires-Dist: numba
Requires-Dist: simphony
Requires-Dist: nlopt (==2.7.1)
Requires-Dist: matplotlib
Requires-Dist: tables
Requires-Dist: tqdm
Requires-Dist: numpy (<1.22) ; python_version == "3.7"
Requires-Dist: numpy (>=1.22) ; python_version >= "3.8"
